Workbook

Sheet Icindekiler
A2: MülkVera - Finansal Projeksiyon Modeli
A3: Sürüm: v1.0 | Güncelleme Tarihi: 2026-08-11
A5: Bölüm | B5: Sayfa Adı | C5: Açıklama | D5: İçerdiği Temel Metrikler | E5: Navigasyon
A6: 1 | B6: Icindekiler | C6: Model haritası ve biçimlendirme açıklamaları | D6: Tüm sayfaların listesi ve renk lejantı | E6: =HYPERLINK("#Icindekiler!A1", "Git →")
A7: 2 | B7: Varsayimlar | C7: Dinamik senaryo seçici ve finansal girdiler | D7: Dolar Kuru, Ortalama Konut Fiyatı, Senaryolar | E7: =HYPERLINK("#Varsayimlar!A1", "Git →")
A8: 3 | B8: Projeksiyonlar | C8: 5 yıllık dinamik gelir ve gider tablosu (TL & USD) | D8: Ciro, Teşvikler, Pazarlama Giderleri, Net Kâr | E8: =HYPERLINK("#Projeksiyonlar!A1", "Git →")
A9: 4 | B9: Degerleme_ve_Yatirim | C9: Yatırımcı geri dönüşü ve şirket değerlemesi | D9: EBITDA Çarpanı, Yatırım Getirisi (IRR), Payback | E9: =HYPERLINK("#Degerleme_ve_Yatirim!A1", "Git →")
A10: 5 | B10: Grafikler | C10: Finansal büyümeyi gösteren görsel grafikler | D10: Gelir ve EBITDA Gelişimi, Yatırım Dağılımı | E10: =HYPERLINK("#Grafikler!A1", "Git →")
A11: 6 | B11: Kontroller | C11: Model formül ve matematik doğrulama tablosu | D11: Formül bütünlüğü ve tutarlılık testleri | E11: =HYPERLINK("#Kontroller!A1", "Git →")
A14: Model Biçimlendirme Lejantı
A16: Mavi Dolgu | B16: Girdi Hücresi (Kullanıcı tarafından değiştirilebilir assumptions)
A17: Yeşil Dolgu | B17: Hesaplama Hücresi (Formülle dinamik olarak üretilen sonuçlar)
A18: Açık Sarı Dolgu | B18: Geçici Veri / Yer Tutucu (İleride gerçek verilerle güncellenmeli)
A19: Koyu Mavi Dolgu | B19: Tablo Başlıkları ve Genel Toplamlar

Sheet Varsayimlar
A2: MülkVera - Finansal Varsayımlar
A4: AKTİF SENARYO SEÇİCİ | B4: 1 | C4: <- DEĞİŞTİRİN (1 = Taban Senaryo, 2 = İyimser Senaryo, 3 = Kötümser Senaryo)
A6: GENEL PAZAR VARYASYONLARI VE PARAMETRELERİ
A7: Dolar Kuru (USD/TRY) | B7: 34
A8: Yıllık Ortalama Konut Fiyatı (TL) | B8: 5000000
A9: Konut Fiyatı Yıllık Artış Oranı (Enflasyon) | B9: 0.15
A10: Alıcı Komisyon Oranı (%) | B10: 0.02
A11: İstanbul Konut Satış Pazarı (Yıllık Adet) | B11: 230000
A12: Pazar Yıllık Adet Artışı (%) | B12: 0.05
A13: Talep Edilen Yatırım Tutarı ($) | B13: 250000
A14: Yatırım Karşılığı Teklif Edilen Hisse (%) | B14: 0.25
A16: YATIRIM FONUNUN KULLANIM DAĞILIMI
A17: Pazarlama ve Dijital Reklam bütçesi | B17: 0.6
A18: 3D Kamera ve Çekim Ekipmanı | B18: 0.2
A19: Yazılım ve Sunucu Geliştirme | B19: 0.1
A20: Operasyonel ve Genel Giderler | B20: 0.1
A23: SENARYO MATRİSİ: 5 YILLIK HEDEFLENEN İŞLEM ADETLERİ
A24: ID | B24: Senaryo Tanımı | C24: Yıl 1 (2026) | D24: Yıl 2 (2027) | E24: Yıl 3 (2028) | F24: Yıl 4 (2029) | G24: Yıl 5 (2030)
A25: 1 | B25: Taban Senaryo (Base Case) | C25: 230 | D25: 750 | E25: 2200 | F25: 5500 | G25: 11000
A26: 2 | B26: İyimser Senaryo (Bull Case) | C26: 350 | D26: 1200 | E26: 3500 | F26: 8000 | G26: 15000
A27: 3 | B27: Kötümser Senaryo (Bear Case) | C27: 120 | D27: 400 | E27: 1000 | F27: 2500 | G27: 5000

Sheet Projeksiyonlar
A2: 5 Yıllık Finansal Gelir ve Gider Projeksiyonları
A4: Finansal Göstergeler (TL & USD) | B4: Metodoloji / Referans | C4: 2026 (Yıl 1) | D4: 2027 (Yıl 2) | E4: 2028 (Yıl 3) | F4: 2029 (Yıl 4) | G4: 2030 (Yıl 5)
A5: OPERASYONEL METRİKLER
A6: Başarılı Satış İşlemi Adedi (Konut) | B6: Dinamik Senaryo Seçici | C6: =INDEX(Varsayimlar!$C$25:$G$27, Varsayimlar!$B$4, 1) | D6: =INDEX(Varsayimlar!$C$25:$G$27, Varsayimlar!$B$4, 2) | E6: =INDEX(Varsayimlar!$C$25:$G$27, Varsayimlar!$B$4, 3) | F6: =INDEX(Varsayimlar!$C$25:$G$27, Varsayimlar!$B$4, 4) | G6: =INDEX(Varsayimlar!$C$25:$G$27, Varsayimlar!$B$4, 5)
A7: Ortalama Konut Değeri (TL) | B7: Varsayımlar B7 | B8 Artış | C7: =Varsayimlar!$B$8 | D7: =C7*(1+Varsayimlar!$B$9) | E7: =D7*(1+Varsayimlar!$B$9) | F7: =E7*(1+Varsayimlar!$B$9) | G7: =F7*(1+Varsayimlar!$B$9)
A8: Toplam Platform İşlem Hacmi (TL) | B8: İşlem Adedi * Ortalama Fiyat | C8: =C6*C7 | D8: =D6*D7 | E8: =E6*E7 | F8: =F6*F7 | G8: =G6*G7
A9: GELİR TABLOSU (TL)
A10: Satış Komisyonu Geliri (TL) - %2 | B10: İşlem Hacmi * Komisyon Oranı (%2) | C10: =C8*Varsayimlar!$B$10 | D10: =D8*Varsayimlar!$B$10 | E10: =E8*Varsayimlar!$B$10 | F10: =F8*Varsayimlar!$B$10 | G10: =G8*Varsayimlar!$B$10
A11: Kiralama Komisyonu Geliri (TL) - (Kira Bedeli vb.) | B11: Satış Gelirinin %15'i | C11: =C10*0.15 | D11: =D10*0.15 | E11: =E10*0.15 | F11: =F10*0.15 | G11: =G10*0.15
A12: Premium Hizmetler ve İlan Öne Çıkarma (TL) | B12: Satış Gelirinin %10'u | C12: =C10*0.10 | D12: =D10*0.10 | E12: =E10*0.10 | F12: =F10*0.10 | G12: =G10*0.10
A13: Veri Analitiği ve Geliştirici Raporlama Abonelikleri (TL) | B13: Satış Gelirinin %5'i | C13: =C10*0.05 | D13: =D10*0.05 | E13: =E10*0.05 | F13: =F10*0.05 | G13: =G10*0.05
A14: Toplam Brüt Gelir (TL) | B14: Gelir Kalemleri Toplamı | C14: =SUM(C10:C13) | D14: =SUM(D10:D13) | E14: =SUM(E10:E13) | F14: =SUM(F10:F13) | G14: =SUM(G10:G13)
A15: Toplam Brüt Gelir (USD) | B15: TL Ciro / Dolar Kuru | C15: =C14/Varsayimlar!$B$7 | D15: =D14/Varsayimlar!$B$7 | E15: =E14/Varsayimlar!$B$7 | F15: =F14/Varsayimlar!$B$7 | G15: =G14/Varsayimlar!$B$7
A16: FAALİYET GİDERLERİ (TL)
A17: 'Ev Getir Kazan' Satıcı Teşvik Giderleri (TL) | B17: Satış Komisyonu * %15 (Teşvik) | C17: =C10*0.15 | D17: =D10*0.15 | E17: =E10*0.15 | F17: =F10*0.15 | G17: =G10*0.15
A18: Pazarlama ve Dijital Reklam Giderleri (TL) | B18: Y1 Yatırımın %60'ı | Sonra %15 Ciro | C18: =Varsayimlar!$B$13*Varsayimlar!$B$17*Varsayimlar!$B$7 | D18: =D14*0.15 | E18: =E14*0.15 | F18: =F14*0.15 | G18: =G14*0.15
A19: Yazılım Bakım ve Sunucu Giderleri (TL) | B19: Y1 %10 Fon | Sonra %15 Artış | C19: =Varsayimlar!$B$13*Varsayimlar!$B$19*Varsayimlar!$B$7 | D19: =C19*1.15 | E19: =D19*1.15 | F19: =E19*1.15 | G19: =F19*1.15
A20: Ekipman Amortismanı ve Çekim Giderleri (TL) | B20: Y1 %20 Fon | Sonra %10 Artış | C20: =Varsayimlar!$B$13*Varsayimlar!$B$18*Varsayimlar!$B$7 | D20: =C20*1.10 | E20: =D20*1.10 | F20: =E20*1.10 | G20: =F20*1.10
A21: Personel ve Ekip Maaş Giderleri (TL) | B21: Y1: 5 Pers. | Y5: 25 Pers. Planı | C21: 2100000 | D21: 3840000 | E21: 6912000 | F21: 12528000 | G21: 21000000
A22: Genel Yönetim ve Kurumsal Giderler (TL) | B22: Y1 %10 Fon | Sonra %10 Artış | C22: =Varsayimlar!$B$13*Varsayimlar!$B$20*Varsayimlar!$B$7 | D22: =C22*1.10 | E22: =D22*1.10 | F22: =E22*1.10 | G22: =F22*1.10
A23: Toplam Faaliyet Giderleri (OPEX) (TL) | B23: Faaliyet Giderleri Toplamı | C23: =SUM(C17:C22) | D23: =SUM(D17:D22) | E23: =SUM(E17:E22) | F23: =SUM(F17:F22) | G23: =SUM(G17:G22)
A24: Toplam Faaliyet Giderleri (OPEX) (USD) | B24: TL OPEX / Dolar Kuru | C24: =C23/Varsayimlar!$B$7 | D24: =D23/Varsayimlar!$B$7 | E24: =E23/Varsayimlar!$B$7 | F24: =F23/Varsayimlar!$B$7 | G24: =G23/Varsayimlar!$B$7
A25: FİNANSAL ÖZET & KÂRLILIK
A26: FAVÖK (EBITDA) (TL) | B26: Ciro (TL) - OPEX (TL) | C26: =C14-C23 | D26: =D14-D23 | E26: =E14-E23 | F26: =F14-F23 | G26: =G14-G23
A27: FAVÖK (EBITDA) (USD) | B27: TL EBITDA / Dolar Kuru | C27: =C26/Varsayimlar!$B$7 | D27: =D26/Varsayimlar!$B$7 | E27: =E26/Varsayimlar!$B$7 | F27: =F26/Varsayimlar!$B$7 | G27: =G26/Varsayimlar!$B$7
A28: FAVÖK Marjı (%) | B28: EBITDA / Toplam Gelir | C28: =IFERROR(C26/C14, 0) | D28: =IFERROR(D26/D14, 0) | E28: =IFERROR(E26/E14, 0) | F28: =IFERROR(F26/F14, 0) | G28: =IFERROR(G26/G14, 0)
A29: Amortisman Gideri (TL) | B29: Kamera & Ekipman / 5 Yıl | C29: =C20/5 | D29: =D20/5 | E29: =E20/5 | F29: =F20/5 | G29: =G20/5
A30: Kurumlar Vergisi (%20) (TL) | B30: Pozitif Kâr üzerinden %20 Vergi | C30: =IF((C26-C29)>0, (C26-C29)*0.20, 0) | D30: =IF((D26-D29)>0, (D26-D29)*0.20, 0) | E30: =IF((E26-E29)>0, (E26-E29)*0.20, 0) | F30: =IF((F26-F29)>0, (F26-F29)*0.20, 0) | G30: =IF((G26-G29)>0, (G26-G29)*0.20, 0)
A31: Net Dönem Kârı (TL) | B31: EBITDA - Amortisman - Vergi | C31: =C26-C29-C30 | D31: =D26-D29-D30 | E31: =E26-E29-E30 | F31: =F26-F29-F30 | G31: =G26-G29-G30
A32: Net Dönem Kârı (USD) | B32: TL Net Kâr / Dolar Kuru | C32: =C31/Varsayimlar!$B$7 | D32: =D31/Varsayimlar!$B$7 | E32: =E31/Varsayimlar!$B$7 | F32: =F31/Varsayimlar!$B$7 | G32: =G31/Varsayimlar!$B$7
A33: Net Kâr Marjı (%) | B33: Net Kâr / Toplam Gelir | C33: =IFERROR(C31/C14, 0) | D33: =IFERROR(D31/D14, 0) | E33: =IFERROR(E31/E14, 0) | F33: =IFERROR(F31/F14, 0) | G33: =IFERROR(G31/G14, 0)

Sheet Degerleme_ve_Yatirim
A2: MülkVera - Şirket Değerlemesi ve Yatırımcı Geri Dönüşü
A4: 5. YIL SONU ŞİRKET DEĞERLEMESİ
A5: EBITDA Çarpanı (Sektör Standardı) | B5: 10 | C5: <- Yatırımcı için varsayılan çarpan
A6: 5. Yıl Sonu EBITDA (USD) | B6: =Projeksiyonlar!G27
A7: Girişim Değeri (USD) (Enterprise Value) | B7: =B5*B6
A10: YATIRIMCI GERİ DÖNÜŞÜ (250.000 $ YATIRIM İÇİN)
A11: Talep Edilen Yatırım Tutarı ($) | B11: =Varsayimlar!$B$13
A12: Teklif Edilen Hisse (%) | B12: =Varsayimlar!$B$14
A13: 5. Yıl Sonu Yatırımcı Hisse Değeri (USD) | B13: =B7*B12
A14: Yatırım Çarpanı (MOIC) | B14: =B13/B11
A15: İç Verim Oranı (IRR) | B15: =(B14)^(1/5)-1
A18: YATIRIM GERİ ÖDEME (PAYBACK) VE NAKİT AKIŞ ANALİZİ
A19: Metrik (USD) | B19: Yıl 0 (Bugün) | C19: Yıl 1 (2026) | D19: Yıl 2 (2027) | E19: Yıl 3 (2028) | F19: Yıl 4 (2029) | G19: Yıl 5 (2030)
A20: Yatırımcı Nakit Akışı (Girdi/Kâr Payı) | B20: =-B11 | C20: =Projeksiyonlar!C32*$B$12 | D20: =Projeksiyonlar!D32*$B$12 | E20: =Projeksiyonlar!E32*$B$12 | F20: =Projeksiyonlar!F32*$B$12 | G20: =Projeksiyonlar!G32*$B$12
A21: Kümülatif Nakit Akışı | B21: =B20 | C21: =B21+C20 | D21: =C21+D20 | E21: =D21+E20 | F21: =E21+F20 | G21: =F21+G20
A22: Yatırım Geri Dönüş Durumu | B22: Yatırım Yapıldı | C22: =IF(AND(B21<0, C21>=0), "Geri Ödeme Sağlandı!", IF(C21>=0, "Kârlı Dönem", "Devam Ediyor")) | D22: =IF(AND(C21<0, D21>=0), "Geri Ödeme Sağlandı!", IF(D21>=0, "Kârlı Dönem", "Devam Ediyor")) | E22: =IF(AND(D21<0, E21>=0), "Geri Ödeme Sağlandı!", IF(E21>=0, "Kârlı Dönem", "Devam Ediyor")) | F22: =IF(AND(E21<0, F21>=0), "Geri Ödeme Sağlandı!", IF(F21>=0, "Kârlı Dönem", "Devam Ediyor")) | G22: =IF(AND(F21<0, G21>=0), "Geri Ödeme Sağlandı!", IF(G21>=0, "Kârlı Dönem", "Devam Ediyor"))

Sheet Grafikler
A2: MülkVera - Projeksiyon Grafikleri ve Görsel Veri Paneli
A4: GRAFİK VERİ KAYNAKLARI (Dinmikte Bağlıdır) | H4: YATIRIM FONU KULLANIM KIRILIMI
A5: Metrik (USD) | B5: 2026 | C5: 2027 | D5: 2028 | E5: 2029 | F5: 2030 | H5: Kullanım Alanı | I5: Yüzde (%)
A6: Toplam Brüt Gelir (USD) | B6: =Projeksiyonlar!C15 | C6: =Projeksiyonlar!D15 | D6: =Projeksiyonlar!E15 | E6: =Projeksiyonlar!F15 | F6: =Projeksiyonlar!G15 | H6: Pazarlama & Reklam | I6: =Varsayimlar!$B$17
A7: FAVÖK (EBITDA) (USD) | B7: =Projeksiyonlar!C27 | C7: =Projeksiyonlar!D27 | D7: =Projeksiyonlar!E27 | E7: =Projeksiyonlar!F27 | F7: =Projeksiyonlar!G27 | H7: 3D Ekipman & Çekim | I7: =Varsayimlar!$B$18
A8: Net Dönem Kârı (USD) | B8: =Projeksiyonlar!C32 | C8: =Projeksiyonlar!D32 | D8: =Projeksiyonlar!E32 | E8: =Projeksiyonlar!F32 | F8: =Projeksiyonlar!G32 | H8: Yazılım & Altyapı | I8: =Varsayimlar!$B$19
H9: Operasyonel & Kurumsal | I9: =Varsayimlar!$B$20

Sheet Kontroller
A2: MülkVera - Finansal Model Güvenilirlik Testleri
A4: No | B4: Güvenilirlik Test Adı | C4: Hedeflenen Değer | D4: Gerçekleşen / Fark | E4: Test Sonucu
A5: 1 | B5: Ciro Tutarlılık Testi (TL Brüt Gelir vs Toplam Parçalar) | C5: 0 | D5: =Projeksiyonlar!C14-SUM(Projeksiyonlar!C10:Projeksiyonlar!C13) | E5: =IF(ABS(D5)<0.01, "BAŞARILI ✅", "HATA ❌")
A6: 2 | B6: Döviz Çevrim Kontrolü (TL Ciro / Kur - USD Ciro) | C6: 0 | D6: =Projeksiyonlar!C15-(Projeksiyonlar!C14/Varsayimlar!$B$7) | E6: =IF(ABS(D6)<0.01, "BAŞARILI ✅", "HATA ❌")
A7: 3 | B7: EBITDA Matematiksel Tutarlılığı (TL Ciro - TL OPEX - EBITDA) | C7: 0 | D7: =Projeksiyonlar!C26-(Projeksiyonlar!C14-Projeksiyonlar!C23) | E7: =IF(ABS(D7)<0.01, "BAŞARILI ✅", "HATA ❌")
A8: 4 | B8: Net Kâr Doğruluk Kontrolü (EBITDA - Amortisman - Vergi - Net Kâr) | C8: 0 | D8: =Projeksiyonlar!C31-(Projeksiyonlar!C26-Projeksiyonlar!C29-Projeksiyonlar!C30) | E8: =IF(ABS(D8)<0.01, "BAŞARILI ✅", "HATA ❌")
